mcp_kanka/__init__.py
mcp_kanka/__main__.py
mcp_kanka/_version.py
mcp_kanka/cli.py
mcp_kanka/converter.py
mcp_kanka/operations.py
mcp_kanka/resources.py
mcp_kanka/service.py
mcp_kanka/tools.py
mcp_kanka/types.py
mcp_kanka/utils.py
mcp_kanka-1.1.0.dist-info/METADATA
mcp_kanka-1.1.0.dist-info/WHEEL
mcp_kanka-1.1.0.dist-info/entry_points.txt
mcp_kanka-1.1.0.dist-info/licenses/LICENSE
mcp_kanka-1.1.0.dist-info/RECORD
