Metadata-Version: 2.4
Name: mcp-kanka
Version: 1.1.0
Summary: MCP server for Kanka API integration
Project-URL: Homepage, https://github.com/ervwalter/mcp-kanka
Project-URL: Documentation, https://github.com/ervwalter/mcp-kanka#readme
Project-URL: Repository, https://github.com/ervwalter/mcp-kanka
Project-URL: Issues, https://github.com/ervwalter/mcp-kanka/issues
Author-email: Erv Walter <erv@ewal.net>
License: MIT
License-File: LICENSE
Keywords: api,kanka,mcp,rpg,tabletop
Classifier: Development Status :: 3 - Alpha
Classifier: Intended Audience :: Developers
Classifier: License :: OSI Approved :: MIT License
Classifier: Programming Language :: Python :: 3
Classifier: Programming Language :: Python :: 3.10
Classifier: Programming Language :: Python :: 3.11
Classifier: Programming Language :: Python :: 3.12
Classifier: Programming Language :: Python :: 3.13
Requires-Python: ==3.13.5
Requires-Dist: beautifulsoup4==4.13.4
Requires-Dist: markdownify==1.1.0
Requires-Dist: mcp==1.9.4
Requires-Dist: mistune==3.1.3
Requires-Dist: python-dotenv==1.1.0
Requires-Dist: python-kanka==2.2.0
